<VAST version="3.0">
  <Ad id="12345">
    <InLine>
      <AdSystem>Sample Ad System</AdSystem>
      <AdTitle>Sample Video Ad</AdTitle>
      <Creatives>
        <Creative>
          <Linear>
            <Duration>00:00:15</Duration>
            <MediaFiles>
              <MediaFile delivery="progressive" type="video/mp4" width="640" height="360">
                <![CDATA[https://sample-videos.com/video123/mp4/720/big_buck_bunny_720p_1mb.mp4]]>
              </MediaFile>
            </MediaFiles>
          </Linear>
        </Creative>
      </Creatives>
    </InLine>
  </Ad>
</VAST>